kg_fuse/__init__.py
kg_fuse/api_client.py
kg_fuse/config.py
kg_fuse/epoch_cache.py
kg_fuse/filesystem.py
kg_fuse/formatters.py
kg_fuse/image_handler.py
kg_fuse/job_tracker.py
kg_fuse/main.py
kg_fuse/models.py
kg_fuse/query_store.py
kg_fuse-0.3.3.dist-info/METADATA
kg_fuse-0.3.3.dist-info/WHEEL
kg_fuse-0.3.3.dist-info/entry_points.txt
kg_fuse-0.3.3.dist-info/RECORD
