Metadata-Version: 2.4
Name: kg-fuse
Version: 0.3.3
Summary: FUSE filesystem for Knowledge Graph - mount your knowledge graph as a filesystem
Project-URL: Homepage, https://github.com/aaronsb/knowledge-graph-system
Project-URL: Repository, https://github.com/aaronsb/knowledge-graph-system.git
Project-URL: Documentation, https://github.com/aaronsb/knowledge-graph-system/blob/main/docs/guides/FUSE_FILESYSTEM.md
Project-URL: Issues, https://github.com/aaronsb/knowledge-graph-system/issues
Author: Aaron Bockelie
License-Expression: MIT
Keywords: filesystem,fuse,knowledge-graph,semantic-search
Classifier: Development Status :: 4 - Beta
Classifier: Environment :: Console
Classifier: Intended Audience :: Developers
Classifier: License :: OSI Approved :: MIT License
Classifier: Operating System :: POSIX :: Linux
Classifier: Programming Language :: Python :: 3.11
Classifier: Programming Language :: Python :: 3.12
Classifier: Topic :: System :: Filesystems
Requires-Python: >=3.11
Requires-Dist: httpx>=0.27.0
Requires-Dist: pyfuse3>=3.3.0
Requires-Dist: tomli-w>=1.0.0
Requires-Dist: trio>=0.25.0
Provides-Extra: dev
Requires-Dist: pytest>=8.0.0; extra == 'dev'
